ia/__init__.py
ia/gaius/__init__.py
ia/gaius/agent_client.py
ia/gaius/back_testing.py
ia/gaius/data_language.py
ia/gaius/data_ops.py
ia/gaius/data_structures.py
ia/gaius/genome_info.py
ia/gaius/kb_ops.py
ia/gaius/manager.py
ia/gaius/prediction_models.py
ia/gaius/thinkflux_client.py
ia/gaius/utils.py
ia/gaius/experimental/__init__.py
ia/gaius/experimental/comcom_client.py
ia/gaius/experimental/genome_optimizer.py
ia/gaius/experimental/sklearn.py
ia/gaius/pvt/__init__.py
ia/gaius/pvt/mongo_interface.py
ia/gaius/pvt/offline_sio.py
ia/gaius/pvt/pvt_utils.py
ia/gaius/tests/__init__.py
ia/gaius/tests/classification.py
ia/gaius/tests/utility.py
ia/scripts/__init__.py
ia/scripts/spawn_agent.py
ia/scripts/spawn_general.py
ia_sdk-0.4.22.data/scripts/ia-spawn
ia_sdk-0.4.22.dist-info/METADATA
ia_sdk-0.4.22.dist-info/WHEEL
ia_sdk-0.4.22.dist-info/top_level.txt
ia_sdk-0.4.22.dist-info/RECORD
