Metadata-Version: 2.1
Name: ia-sdk
Version: 0.4.22
Summary: SDK for Intelligent Artifact's GAIuS agents.
Home-page: https://intelligent-artifacts.com
Author: Intelligent Artifacts
Author-email: support@intelligent-artifacts.com
Project-URL: Documentation, https://intelligent-artifacts.bitbucket.io
Classifier: Programming Language :: Python :: 3
Classifier: License :: OSI Approved :: MIT License
Classifier: Operating System :: OS Independent
Requires-Dist: requests
Requires-Dist: pymongo
Requires-Dist: numpy
Requires-Dist: sty
Requires-Dist: docker
Requires-Dist: platformdirs
Requires-Dist: retry
Requires-Dist: filelock
Provides-Extra: pvt
Requires-Dist: pandas ; extra == 'pvt'
Requires-Dist: plotly ; extra == 'pvt'
Requires-Dist: scikit-learn ; extra == 'pvt'
Requires-Dist: matplotlib ; extra == 'pvt'
Requires-Dist: ipywidgets ; extra == 'pvt'
Requires-Dist: ipython ; extra == 'pvt'
Requires-Dist: tqdm ; extra == 'pvt'
Requires-Dist: kaleido ; extra == 'pvt'
Requires-Dist: networkx ; extra == 'pvt'
Requires-Dist: ipycytoscape ; extra == 'pvt'
